xpyth_parser/__init__.py
xpyth_parser/parse.py
xpyth_parser/conversion/__init__.py
xpyth_parser/conversion/function.py
xpyth_parser/conversion/primaries.py
xpyth_parser/conversion/qname.py
xpyth_parser/conversion/tests.py
xpyth_parser/conversion/functions/__init__.py
xpyth_parser/conversion/functions/generic.py
xpyth_parser/conversion/functions/xbrl.py
xpyth_parser/grammar/__init__.py
xpyth_parser/grammar/expressions.py
xpyth_parser/grammar/literals.py
xpyth_parser/grammar/qualified_names.py
xpyth_parser-0.0.10.dist-info/LICENSE
xpyth_parser-0.0.10.dist-info/METADATA
xpyth_parser-0.0.10.dist-info/WHEEL
xpyth_parser-0.0.10.dist-info/top_level.txt
xpyth_parser-0.0.10.dist-info/RECORD
