Metadata-Version: 2.1
Name: xpyth-parser
Version: 0.0.10
Summary: An XPath 3.1 Parser
Home-page: https://github.com/ekaats/xpyth_parser
Author: Erwin Kaats
Author-email: egit@tuta.io
License: UNKNOWN
Project-URL: Bug Tracker, https://github.com/ekaats/xpyth_parser/issues
Platform: UNKNOWN
Classifier: Programming Language :: Python :: 3
Classifier: License :: OSI Approved :: GNU General Public License v3 or later (GPLv3+)
Classifier: Development Status :: 3 - Alpha
Requires-Python: >=3.6
License-File: LICENSE
Requires-Dist: lxml
Requires-Dist: pyparsing
Requires-Dist: isodate
